{
  "id": "MAP_FERRITE_CAVE_G",
  "name": "FerriteCaveG",
  "layout": "LAYOUT_FERRITE_CAVE_G",
  "music": "MUS_VICTORY_ROAD",
  "region_map_section": "MAPSEC_FERRITE_CAVE",
  "requires_flash": false,
  "weather": "WEATHER_NONE",
  "map_type": "MAP_TYPE_UNDERGROUND",
  "allow_cycling": true,
  "allow_escaping": true,
  "allow_running": true,
  "show_map_name": true,
  "battle_scene": "MAP_BATTLE_SCENE_NORMAL",
  "connections": 0,
  "object_events": [

  ],
  "warp_events": [

  ],
  "coord_events": [

  ],
  "bg_events": [

  ]
}
